email_extractor_unicode/__init__.py
email_extractor_unicode/extractor.py
email_extractor_unicode-1.3.0.dist-info/LICENSE.rst
email_extractor_unicode-1.3.0.dist-info/METADATA
email_extractor_unicode-1.3.0.dist-info/WHEEL
email_extractor_unicode-1.3.0.dist-info/top_level.txt
email_extractor_unicode-1.3.0.dist-info/RECORD
