Metadata-Version: 2.1
Name: email_extractor_unicode
Version: 1.3.0
Summary: Extract Emails Using Phone Number
Home-page: https://t.me/iamunicode
Author: Unicode
License: MIT
Keywords: emails
Classifier: Development Status :: 5 - Production/Stable
Classifier: Intended Audience :: Education
Classifier: Operating System :: Microsoft :: Windows :: Windows 10
Classifier: License :: OSI Approved :: MIT License
Classifier: Programming Language :: Python :: 3
Requires-Python: >=3.12
License-File: LICENSE.rst
Requires-Dist: undetected-chromedriver
Requires-Dist: beautifulsoup4
Requires-Dist: setuptools
